rdflib_sqlalchemy/__init__.py
rdflib_sqlalchemy/base.py
rdflib_sqlalchemy/constants.py
rdflib_sqlalchemy/sql.py
rdflib_sqlalchemy/statistics.py
rdflib_sqlalchemy/store.py
rdflib_sqlalchemy/tables.py
rdflib_sqlalchemy/termutils.py
rdflib_sqlalchemy/types.py
rdflib_sqlalchemy-0.5.4.dist-info/LICENSE.txt
rdflib_sqlalchemy-0.5.4.dist-info/METADATA
rdflib_sqlalchemy-0.5.4.dist-info/WHEEL
rdflib_sqlalchemy-0.5.4.dist-info/entry_points.txt
rdflib_sqlalchemy-0.5.4.dist-info/top_level.txt
rdflib_sqlalchemy-0.5.4.dist-info/RECORD
